ancypwn/__init__.py
ancypwn/ancypwn.py
ancypwn/ancypwn.tmp.py
ancypwn/server.py
ancypwn/util.py
ancypwn-1.0.0.dist-info/LICENSE.md
ancypwn-1.0.0.dist-info/METADATA
ancypwn-1.0.0.dist-info/WHEEL
ancypwn-1.0.0.dist-info/entry_points.txt
ancypwn-1.0.0.dist-info/top_level.txt
ancypwn-1.0.0.dist-info/RECORD
